{
  "pages": [
    {
      "path": "pages/index/index",
      "style": {
        "navigationBarTitleText": "品牌首页"
      }
    },
    {
      "path": "pages/index/brand/index",
      "style": {
        "navigationBarTitleText": "品牌简介"
      }
    },
    {
      "path": "pages/index/projectInfo/index",
      "style": {
        "navigationBarTitleText": "项目资讯"
      }
    },
    {
      "path": "pages/index/activeInfo/index",
      "style": {
        "navigationBarTitleText": "活动详情"
      }
    },
    {
      "path": "pages/login/index",
      "style": {
        "navigationBarTitleText": "授权"
      }
    },
    {
      "path": "pages/project/index",
      "style": {
        "navigationBarTitleText": "天安·云境"
      }
    },
    {
      "path": "pages/project/house-detail/index",
      "style": {
        "navigationBarTitleText": "楼盘详情"
      }
    },
    {
      "path": "pages/project/projectAlbum/index",
      "style": {
        "navigationBarTitleText": "项目相册"
      }
    },
    {
      "path": "pages/project/salesConsultant/index",
      "style": {
        "navigationBarTitleText": "销售顾问"
      }
    },
    {
      "path": "pages/project/createNotice/index",
      "style": {
        "navigationBarTitleText": "名片"
      }
    },
    {
      "path": "pages/project/pactHouse/index",
      "style": {
        "navigationBarTitleText": "预约看房"
      }
    },
    {
      "path": "pages/project/counselorCard/index",
      "style": {
        "navigationBarTitleText": "销售名片"
      }
    },
    {
      "path": "pages/shop/index",
      "style": {
        "navigationBarTitleText": "积分商城"
      }
    },
    {
      "path": "pages/shop/goods-detail/index",
      "style": {
        "navigationBarTitleText": "商品详情"
      }
    },
    {
      "path": "pages/shop/rule/index",
      "style": {
        "navigationBarTitleText": "积分规则"
      }
    },
    {
      "path": "pages/shop/apply/index",
      "style": {
        "navigationBarTitleText": "报名"
      }
    },
    {
      "path": "pages/mine/index",
      "style": {
        "navigationBarTitleText": "我的"
      }
    },
    {
      "path": "pages/mine/my-info/index",
      "style": {
        "navigationBarTitleText": "我的信息"
      }
    },
    {
      "path": "pages/mine/my-integral/index",
      "style": {
        "navigationBarTitleText": "我的积分"
      }
    },
    {
      "path": "pages/mine/my-activite/index",
      "style": {
        "navigationBarTitleText": "我的活动"
      }
    },
    {
      "path": "pages/mine/my-activite/detailInfo/index",
      "style": {
        "navigationBarTitleText": "活动详情"
      }
    },
    {
      "path": "pages/mine/my-gift/index",
      "style": {
        "navigationBarTitleText": "我的礼品"
      }
    },
    {
      "path": "pages/mine/my-order/index",
      "style": {
        "navigationBarTitleText": "我的预约"
      }
    },
    {
      "path": "pages/mine/my-collect/index",
      "style": {
        "navigationBarTitleText": "我的收藏"
      }
    },
    {
      "path": "pages/webview/index",
      "style": {
        "navigationBarTitleText": "webview"
      }
    },
    {
      "path": "pages/webviewvr/index",
      "style": {
        "navigationBarTitleText": "webviewvr"
      }
    }
  ],
  "tabBar": {
    "color": "#61b7b6",
    "selectedColor": "#dbb674",
    "backgroundColor": "#f4f4f4",
    "borderStyle": "white",
    "list": [
      {
        "pagePath": "pages/index/index",
        "text": "首页",
        "iconPath": "./static/styles/icon/home.png",
        "selectedIconPath": "./static/styles/icon/home_on.png"
      },
      {
        "pagePath": "pages/project/index",
        "text": "天安·云境",
        "iconPath": "./static/styles/icon/project.png",
        "selectedIconPath": "./static/styles/icon/project_on.png"
      },
      {
        "pagePath": "pages/shop/index",
        "text": "积分商城",
        "iconPath": "./static/styles/icon/shop.png",
        "selectedIconPath": "./static/styles/icon/shop_on.png"
      },
      {
        "pagePath": "pages/mine/index",
        "text": "我的",
        "iconPath": "./static/styles/icon/mine.png",
        "selectedIconPath": "./static/styles/icon/mine_on.png"
      }
    ]
  },
  "globalStyle": {
    "navigationBarTextStyle": "black",
    "navigationBarTitleText": "uni-app",
    "navigationBarBackgroundColor": "#62b2af",
    "backgroundColor": "#F8F8F8",
    "usingComponents": {
      "painter": "/static/painter/painter"
    }
  },
  "easycom": {
    "autoscan": true,
    "custom": {
      "^uni-(.*)": "@dcloudio/uni-ui/lib/uni-$1/uni-$1.vue"
    }
  }
}
